{"container_type": "Author", "filled": ["basics", "publications", "indices", "counts"], "scholar_id": "Vm54jdoAAAAJ", "source": "AUTHOR_PROFILE_PAGE", "name": "Jiaxin Wang", "url_picture": "https://scholar.googleusercontent.com/citations?view_op=view_photo&user=Vm54jdoAAAAJ&citpid=4", "affiliation": "Nanjing University", "organization": 8752502527516415164, "interests": ["Blockchain", "Graph Neural Network", "Open Source Software", "Diffusion of Innovation", "Predictive Modeling"], "email_domain": "@smail.nju.edu.cn", "homepage": "https://thomaswangjiaxin.github.io/", "citedby": 18, "publications": {"Vm54jdoAAAAJ:Wp0gIr-vW9MC": {"container_type": "Publication", "source": "AUTHOR_PUBLICATION_ENTRY", "bib": {"title": "Identifying Crypto Addresses with Gambling Behaviors: A Graph Neural Network Approach", "pub_year": "2023"}, "filled": false, "author_pub_id": "Vm54jdoAAAAJ:Wp0gIr-vW9MC", "num_citations": 5, "citedby_url": "https://scholar.google.com/scholar?oi=bibs&hl=en&cites=520615225200728351", "cites_id": ["520615225200728351"]}, "Vm54jdoAAAAJ:8k81kl-MbHgC": {"container_type": "Publication", "source": "AUTHOR_PUBLICATION_ENTRY", "bib": {"title": "Research on UAV Image Recognition Based on Convolutional Neural Network", "pub_year": "2020"}, "filled": false, "author_pub_id": "Vm54jdoAAAAJ:8k81kl-MbHgC", "num_citations": 5, "citedby_url": "https://scholar.google.com/scholar?oi=bibs&hl=en&cites=8177568694674675006,13832138862231166011", "cites_id": ["8177568694674675006", "13832138862231166011"]}, "Vm54jdoAAAAJ:IWHjjKOFINEC": {"container_type": "Publication", "source": "AUTHOR_PUBLICATION_ENTRY", "bib": {"title": "Gamblers or Delegatees: Identifying Hidden Participant Roles in Crypto Casinos", "pub_year": "2025"}, "filled": false, "author_pub_id": "Vm54jdoAAAAJ:IWHjjKOFINEC", "num_citations": 2, "citedby_url": "https://scholar.google.com/scholar?oi=bibs&hl=en&cites=16862177806428811710", "cites_id": ["16862177806428811710"]}, "Vm54jdoAAAAJ:mVmsd5A6BfQC": {"container_type": "Publication", "source": "AUTHOR_PUBLICATION_ENTRY", "bib": {"title": "Smoke and Mirrors: Uncovering Hidden Delegatees in Crypto Casinos", "pub_year": "2025"}, "filled": false, "author_pub_id": "Vm54jdoAAAAJ:mVmsd5A6BfQC", "num_citations": 2, "citedby_url": "https://scholar.google.com/scholar?oi=bibs&hl=en&cites=16116063811360125672", "cites_id": ["16116063811360125672"]}, "Vm54jdoAAAAJ:qxL8FJ1GzNcC": {"container_type": "Publication", "source": "AUTHOR_PUBLICATION_ENTRY", "bib": {"title": "Unravelling Stablecoin-Favored Ecosystem: Extracting, Exploring On-Chain Data from TRON Blockchain", "pub_year": "2024"}, "filled": false, "author_pub_id": "Vm54jdoAAAAJ:qxL8FJ1GzNcC", "num_citations": 2, "citedby_url": "https://scholar.google.com/scholar?oi=bibs&hl=en&cites=16291742400705179583", "cites_id": ["16291742400705179583"]}, "Vm54jdoAAAAJ:hFOr9nPyWt4C": {"container_type": "Publication", "source": "AUTHOR_PUBLICATION_ENTRY", "bib": {"title": "Behind the scenes in metaverses: exploring undercover role cooperations with cryptocurrency transactions through an intellectual capital lens", "pub_year": "2025"}, "filled": false, "author_pub_id": "Vm54jdoAAAAJ:hFOr9nPyWt4C", "num_citations": 1, "citedby_url": "https://scholar.google.com/scholar?oi=bibs&hl=en&cites=5450222987555946356", "cites_id": ["5450222987555946356"]}, "Vm54jdoAAAAJ:9ZlFYXVOiuMC": {"container_type": "Publication", "source": "AUTHOR_PUBLICATION_ENTRY", "bib": {"title": "Targeting the Achilles’ Heel: A GNN Framework for Dismantling Cryptocurrency War-Financing Networks", "pub_year": "2024"}, "filled": false, "author_pub_id": "Vm54jdoAAAAJ:9ZlFYXVOiuMC", "num_citations": 1, "citedby_url": "https://scholar.google.com/scholar?oi=bibs&hl=en&cites=10150536063045587513", "cites_id": ["10150536063045587513"]}, "Vm54jdoAAAAJ:_Qo2XoVZTnwC": {"container_type": "Publication", "source": "AUTHOR_PUBLICATION_ENTRY", "bib": {"title": "SoK: Web3 RegTech for Cryptocurrency VASP AML/CFT Compliance", "pub_year": "2025"}, "filled": false, "author_pub_id": "Vm54jdoAAAAJ:_Qo2XoVZTnwC", "num_citations": 0}, "Vm54jdoAAAAJ:R3hNpaxXUhUC": {"container_type": "Publication", "source": "AUTHOR_PUBLICATION_ENTRY", "bib": {"title": "Architectural patterns for blockchain-enabled federated learning: A systematic literature review", "pub_year": "2025"}, "filled": false, "author_pub_id": "Vm54jdoAAAAJ:R3hNpaxXUhUC", "num_citations": 0}, "Vm54jdoAAAAJ:mB3voiENLucC": {"container_type": "Publication", "source": "AUTHOR_PUBLICATION_ENTRY", "bib": {"title": "Decoding TRON: A Comprehensive Framework for Large-Scale Blockchain Data Extraction and Exploration", "pub_year": "2025"}, "filled": false, "author_pub_id": "Vm54jdoAAAAJ:mB3voiENLucC", "num_citations": 0}, "Vm54jdoAAAAJ:-f6ydRqryjwC": {"container_type": "Publication", "source": "AUTHOR_PUBLICATION_ENTRY", "bib": {"title": "AI for Web3 Business Ecosystems: A Conceptual Framework", "pub_year": "2025"}, "filled": false, "author_pub_id": "Vm54jdoAAAAJ:-f6ydRqryjwC", "num_citations": 0}, "Vm54jdoAAAAJ:7PzlFSSx8tAC": {"container_type": "Publication", "source": "AUTHOR_PUBLICATION_ENTRY", "bib": {"title": "融合多维学术特征的引文推荐：一种基于异质图卷积网络的方法", "pub_year": "2025"}, "filled": false, "author_pub_id": "Vm54jdoAAAAJ:7PzlFSSx8tAC", "num_citations": 0}, "Vm54jdoAAAAJ:dhFuZR0502QC": {"container_type": "Publication", "source": "AUTHOR_PUBLICATION_ENTRY", "bib": {"title": "区块链混币监管技术研究综述", "pub_year": "2025"}, "filled": false, "author_pub_id": "Vm54jdoAAAAJ:dhFuZR0502QC", "num_citations": 0}, "Vm54jdoAAAAJ:aqlVkmm33-oC": {"container_type": "Publication", "source": "AUTHOR_PUBLICATION_ENTRY", "bib": {"title": "区块链游戏生态的角色动态识别与演化分析——以 Axie Infinity 为例", "pub_year": "2024"}, "filled": false, "author_pub_id": "Vm54jdoAAAAJ:aqlVkmm33-oC", "num_citations": 0}, "Vm54jdoAAAAJ:4TOpqqG69KYC": {"container_type": "Publication", "source": "AUTHOR_PUBLICATION_ENTRY", "bib": {"title": "加密数字货币监管技术研究综述", "pub_year": "2023"}, "filled": false, "author_pub_id": "Vm54jdoAAAAJ:4TOpqqG69KYC", "num_citations": 0}, "Vm54jdoAAAAJ:_kc_bZDykSQC": {"container_type": "Publication", "source": "AUTHOR_PUBLICATION_ENTRY", "bib": {"title": "加密数字货币恐怖融资监管: 交易模式分析与异常实体识别", "pub_year": "2023"}, "filled": false, "author_pub_id": "Vm54jdoAAAAJ:_kc_bZDykSQC", "num_citations": 0}, "Vm54jdoAAAAJ:5nxA0vEk-isC": {"container_type": "Publication", "source": "AUTHOR_PUBLICATION_ENTRY", "bib": {"title": "Detecting and Characterizing Abnormal Addresses in the Bitcoin Transaction System: A Social Network Approach", "pub_year": "2022"}, "filled": false, "author_pub_id": "Vm54jdoAAAAJ:5nxA0vEk-isC", "num_citations": 0}}, "citedby5y": 17, "hindex": 2, "hindex5y": 2, "i10index": 0, "i10index5y": 0, "cites_per_year": {"2022": 2, "2023": 1, "2024": 4, "2025": 9, "2026": 1}, "updated": "2026-01-16 08:28:10.439182"}